{"is_source_file": false, "format": "", "description": "", "external_files": [], "external_methods": [], "published": [], "classes": [], "methods": [], "calls": [], "search-terms": [], "state": 2, "file_id": 1, "knowledge_revision": 4, "git_revision": "f29ce057d8537519e3d81655ebc1d989716bd355", "hash": "836b747d13f9ed5951c42ca4f7b3ba76", "format-version": 4, "code-base-name": "android_frontend", "filename": "android_frontend/init_script.sh", "revision_history": [{"4": "f29ce057d8537519e3d81655ebc1d989716bd355"}]}